{
    "Bienes muebles": [
        {
            "Identificador": "SUB-AT-2025-25R2886002041",
            "Categor\u00eda": "Otros bienes y derechos",
            "Fin": "2025-09-29",
            "Tasaci\u00f3n": 14796547.0,
            "Puja m\u00ednima": 887792.82,
            "Tramos": 10000.0,
            "Dep\u00f3sito": 887792.82,
            "Descripci\u00f3n": "14.796.547 PARTICIPACIONES SOCIALES DE 1 \u20ac DE VALOR NOMINAL CADA UNA DE       ELLAS, NUMERADAS CORRELATIVAMENTE DE LA 48.568.809 AL N\u00daMERO 63.365.355      AMBOS INCLUSIVE.",
            "Puja m\u00e1s alta": "PREMIUM_INTEGER"
        },
        {
            "Identificador": "SUB-AT-2025-25R2886002037",
            "Categor\u00eda": "Otros bienes y derechos",
            "Fin": "2025-09-29",
            "Tasaci\u00f3n": 568053.08,
            "Puja m\u00ednima": 45444.25,
            "Tramos": 2000.0,
            "Dep\u00f3sito": 45444.24,
            "Descripci\u00f3n": "ACCIONES DE LA SOCIEDAD PATRO 68 S.A NIF: B49128879 : NUDA PROPIEDAD DE 30    ACCIONES N\u00ba 251 A 280, AMBAS INCLUSIVE. PLENO DOMINIO DE LA MITAD            PROINDIVISO DE 120 ACCIONES N\u00ba 581 A 700, AMBAS INCLUSIVE. PLENO DOMINIO DE  71 ACCIONES (N\u00ba 1252 A 1322, AMBAS INCLUSIVE).",
            "Puja m\u00e1s alta": "PREMIUM_INTEGER"
        },
        {
            "Identificador": "SUB-JA-2025-241724",
            "Categor\u00eda": "Otros bienes y derechos",
            "Fin": "2025-09-29",
            "Tasaci\u00f3n": 304913.0,
            "Puja m\u00ednima": 0.0,
            "Tramos": 6098.26,
            "Dep\u00f3sito": 15245.65,
            "Descripci\u00f3n": "Posibilidades de pesca que corresponden al Buque          denominado ARCA UNO (IMO 9252149) en el \u201ccenso unificado de palangre de superficie\u201d dependiente de la Secretar\u00eda General de Pesca.  Seg\u00fan la Resoluci\u00f3n de 22 de febrero de 2024, de la Secretar\u00eda General de Pesca, por la que se publica la actualizaci\u00f3n del censo unificado de palangre de superficie (BOE 29 de febrero), el buque ARCA UNO presenta la cuota actual de 1,016378% para realizar la pesca de pez espada (SWO)con el arte de palangre de superficie en el Atl\u00e1ntico Norte en las siguientes zonas:          ZONA 2 (C.N. hasta 80 millas del Atl. Norte)          ZONA 3 (C.N. por fuera 80 millas y aguas intern. Del Atl.          Norte)          ZONA 5 Oc\u00e9ano \u00cdndico (CTOI)          ZONA 6 Oc\u00e9ano Pac\u00edfico (CIAT)          ZONA 7 Oc\u00e9ano Pac\u00edfico Central y Oeste (CCPOC)",
            "Puja m\u00e1s alta": "PREMIUM_INTEGER"
        },
        {
            "Identificador": "SUB-JV-2025-251448",
            "Categor\u00eda": "Buques",
            "Fin": "2025-09-29",
            "Tasaci\u00f3n": 1080000.0,
            "Puja m\u00ednima": 459000.0,
            "Tramos": 36720.0,
            "Dep\u00f3sito": 91800.0,
            "Descripci\u00f3n": "SEGUNDA SUBASTA CARGUERO RAS, IMO 9040663 CON BANDERA DE TANZANIA DE 66.2 M/ESLORA Y 12.82 DE MANGA, MOTOR DE 672 KW- Las \u00faltimas inspecciones de las que se tiene constancia del buque son el          22/09/2022 en Italia bajo el paraguas del memor\u00e1ndum Par\u00eds MoU,          apreci\u00e1ndose numerosas deficiencias (15) propias de un buque de avanzada          edad con poco mantenimiento, pero siendo deficiencias menores no          acreedoras de la detenci\u00f3n del buque, y en Turqu\u00eda el 15/05/2024 bajo el          memor\u00e1ndum Mediterranean MoU, con siete deficiencias, sin detenci\u00f3n.          - A pesar de su edad, el buque se encuentra en un estado de conservaci\u00f3n          razonable para navegar. Es un buque viejo (30 a\u00f1os) apreci\u00e1ndose signos de          su edad en el casco, no obstante, se ha invertido dinero en su          mantenimiento, pudi\u00e9ndose apreciar instalaciones de modernizaci\u00f3n          recientes, como por ejemplo los grupos electr\u00f3genos y cuadro principal, el          grupo generador de emergencia, diversas bombas y piezas de los          compresores, planta de tratamiento de agua de lastre, y tuber\u00eda renovada          entre otros elementos. Dispone de todos los equipos de seguridad y          radiocomunicaciones, estando algunos de ellos en vigor, aunque es posible          que necesite realizar la revisi\u00f3n anual de la gran mayor\u00eda de ellos.",
            "Puja m\u00e1s alta": "PREMIUM_INTEGER"
        },
        {
            "Identificador": "SUB-AT-2025-25R2886002052",
            "Categor\u00eda": "Otros bienes y derechos",
            "Fin": "2025-09-29",
            "Tasaci\u00f3n": 571500.0,
            "Puja m\u00ednima": 34290.0,
            "Tramos": 2000.0,
            "Dep\u00f3sito": 34290.0,
            "Descripci\u00f3n": "PARTICIPACIONES SOCIALES DE LA SOCIEDAD CONSTRUCCIONES Y PROMOCIONES          MELIVAL, S.L (B52031234 ). DE LA 1 A 150 (AMBAS INCLUSIVE) Y DE LA 96.001 A  LA 153.000 (AMBAS INCLUSIVE)..",
            "Puja m\u00e1s alta": "PREMIUM_INTEGER"
        },
        {
            "Identificador": "SUB-AT-2025-25R3586002009",
            "Categor\u00eda": "Otros bienes y derechos",
            "Fin": "2025-09-29",
            "Tasaci\u00f3n": 1710.2,
            "Puja m\u00ednima": 171.02,
            "Tramos": 200.0,
            "Dep\u00f3sito": 171.02,
            "Descripci\u00f3n": "10% DE LAS PARTICIPACIONES EN LA SOCIEDAD EDIFICIOS LANZAROTE SL (NIF         B35959865). OBJETO SOCIAL: PROMOCI\u00d3N, ORDENACI\u00d3N, URBANIZACI\u00d3N, Y            PARCELACI\u00d3N DE TERENOS, COMPRA, VENTA, ADMINISTRACI\u00d3N, ARRENDAMIENTO Y       CONSTRUCCI\u00d3N DE FINCAS.",
            "Puja m\u00e1s alta": "PREMIUM_INTEGER"
        },
        {
            "Identificador": "SUB-AT-2025-25R2886002046",
            "Categor\u00eda": "Derechos de propiedad industrial",
            "Fin": "2025-09-29",
            "Tasaci\u00f3n": 1327.88,
            "Puja m\u00ednima": 132.79,
            "Tramos": 100.0,
            "Dep\u00f3sito": 132.78,
            "Descripci\u00f3n": "REGISTRO DE MARCA NACIONAL N\u00ba M4015807 INSCRITO EN LA OFICINA ESPA\u00d1OLA DE     PATENTES Y MARCAS",
            "Puja m\u00e1s alta": "PREMIUM_INTEGER"
        },
        {
            "Identificador": "SUB-AT-2025-25R3586002008",
            "Categor\u00eda": "Otros bienes y derechos",
            "Fin": "2025-09-29",
            "Tasaci\u00f3n": 15400.8,
            "Puja m\u00ednima": 1540.08,
            "Tramos": 500.0,
            "Dep\u00f3sito": 1540.08,
            "Descripci\u00f3n": "90% DE LAS PARTICIPACIONES EN LA SOCIEDAD EDIFICIOS LANZAROTE SL (NIF         B35959865). OBJETO SOCIAL: PROMOCI\u00d3N, ORDENACI\u00d3N, URBANIZACI\u00d3N, Y            PARCELACI\u00d3N DE TERENOS, COMPRA, VENTA, ADMINISTRACI\u00d3N, ARRENDAMIENTO Y       CONSTRUCCI\u00d3N DE FINCAS.",
            "Puja m\u00e1s alta": "PREMIUM_INTEGER"
        },
        {
            "Identificador": "SUB-JV-2025-251447",
            "Categor\u00eda": "Buques",
            "Fin": "2025-09-29",
            "Tasaci\u00f3n": 85000.0,
            "Puja m\u00ednima": 42500.0,
            "Tramos": 2600.0,
            "Dep\u00f3sito": 17000.0,
            "Descripci\u00f3n": "EMBARCACION \"NIGHT FALLS\" N\u00ba REGISTRO SSR178767, BANDERA DE REINO UNIDO",
            "Puja m\u00e1s alta": "PREMIUM_INTEGER"
        },
        {
            "Identificador": "SUB-AT-2025-25R0786002002",
            "Categor\u00eda": "Otros bienes y derechos",
            "Fin": "2025-09-22",
            "Tasaci\u00f3n": 188319.2,
            "Puja m\u00ednima": 18831.92,
            "Tramos": 2000.0,
            "Dep\u00f3sito": 18831.92,
            "Descripci\u00f3n": "4.148 PARTICIPACIONES SOCIALES DE LA ENTIDAD N\u00daMERO 5 MALLORCA, S.L. DE 31 \u20ac  DE VALOR NOMINAL.",
            "Puja m\u00e1s alta": "PREMIUM_INTEGER"
        },
        {
            "Identificador": "SUB-AT-2025-25R2886002031",
            "Categor\u00eda": "Otros bienes y derechos",
            "Fin": "2025-09-29",
            "Tasaci\u00f3n": 94747.42,
            "Puja m\u00ednima": 7579.79,
            "Tramos": 2000.0,
            "Dep\u00f3sito": 7579.79,
            "Descripci\u00f3n": "81265 PARTICIPACIONES SOCIALES DE LA SOCIEDAD RODRIGUEZ CALVIN SL             (B83512293), DE LA 659.471 A LA 740.735 AMBAS INCLUSIVE",
            "Puja m\u00e1s alta": "PREMIUM_INTEGER"
        },
        {
            "Identificador": "SUB-AT-2025-25R3886002008",
            "Categor\u00eda": "Otros bienes y derechos",
            "Fin": "2025-09-15",
            "Tasaci\u00f3n": 1172053.44,
            "Puja m\u00ednima": 117205.34,
            "Tramos": 5000.0,
            "Dep\u00f3sito": 117205.34,
            "Descripci\u00f3n": "11.646 PARTICIPACIONES DEL N\u00daMERO 42.041 AL 53.685 TOTAL NOMINAL              1.164.600,00 QUE SUPONEN UN 22% DEL CAPITAL SOCIAL DE LA ENTIDAD VENT DE     PORT-BOU SL B17949017",
            "Puja m\u00e1s alta": "PREMIUM_INTEGER"
        }
    ],
    "Veh\u00edculos": [
        {
            "Identificador": "SUB-AT-2025-25R2886002050",
            "Categor\u00eda": "Turismos",
            "Fin": "2025-09-29",
            "Tasaci\u00f3n": 10302.0,
            "Puja m\u00ednima": 1030.2,
            "Tramos": 500,
            "Dep\u00f3sito": 1030.2,
            "Descripci\u00f3n": "FURGONETA 2411KWC  VOLKSWAGEN  CRAFTER",
            "Puja m\u00e1s alta": "PREMIUM_INTEGER",
            "Marca": "VOLKSWAGEN",
            "Provincia": "-"
        },
        {
            "Identificador": "SUB-JC-2025-247805",
            "Categor\u00eda": "Otros",
            "Fin": "2025-09-24",
            "Tasaci\u00f3n": 0.0,
            "Puja m\u00ednima": 100.0,
            "Tramos": "Sin tramos",
            "Dep\u00f3sito": 1000.0,
            "Descripci\u00f3n": "LOTE 2.- Motocicleta Suzuki VL 800. A\u00f1o 2006. No constan cargas en el Registro de Bienes Muebles. Fecha de validez de la \u00faltima ITV, 4 de julio de 2023. Seg\u00fan manifiesta la administraci\u00f3n concursal, la moto est\u00e1 en funcionamiento pero en estado de usada. Tener en cuenta que por la fecha de matriculaci\u00f3n el veh\u00edculo tiene 19 a\u00f1os. Est\u00e1 en garaje de la vivienda del concursado, sito en Calle Europa, n\u00famero 5, piso 2do, puerta B, de Cartagena 30300 Murcia. Puede ser visitada",
            "Puja m\u00e1s alta": "PREMIUM_INTEGER",
            "Marca": "-",
            "Provincia": "-"
        },
        {
            "Identificador": "SUB-AT-2025-25R4186002050",
            "Categor\u00eda": "Turismos",
            "Fin": "2025-09-15",
            "Tasaci\u00f3n": 11505.0,
            "Puja m\u00ednima": 1150.5,
            "Tramos": 500,
            "Dep\u00f3sito": 1150.5,
            "Descripci\u00f3n": "VEHICULO 2911KXZ   FORD MONDEO",
            "Puja m\u00e1s alta": "PREMIUM_INTEGER",
            "Marca": "FORD",
            "Provincia": "-"
        },
        {
            "Identificador": "SUB-AT-2025-25R4186002054",
            "Categor\u00eda": "Turismos",
            "Fin": "2025-09-15",
            "Tasaci\u00f3n": 5009.37,
            "Puja m\u00ednima": 500.94,
            "Tramos": 200,
            "Dep\u00f3sito": 500.93,
            "Descripci\u00f3n": "TURISMO NACIONAL/IMPORTAC 5150JWM  VOLVO  V40 CROSS COUNTRY",
            "Puja m\u00e1s alta": "PREMIUM_INTEGER",
            "Marca": "VOLVO",
            "Provincia": "-"
        },
        {
            "Identificador": "SUB-JV-2025-251166",
            "Categor\u00eda": "Turismos",
            "Fin": "2025-09-29",
            "Tasaci\u00f3n": 13886.0,
            "Puja m\u00ednima": 6943.0,
            "Tramos": 350,
            "Dep\u00f3sito": 2777.2,
            "Descripci\u00f3n": "TURISMO          Marca BMW          Modelo 530D          Matr\u00edcula 8516HWW          Bastidor WBAFW71070C897121          Primera matriculaci\u00f3n 12/05/2011          Contrase\u00f1a de homologaci\u00f3n E1*2007/46*0363*04          Carburante Diesel          Color Negro          Cilindrada 2.993 c.c.          Potencia 258 CV (190 Kw)          Kil\u00f3metros 250.855          N\u00famero de plazas 5 plazas          Acabados M (s\u00f3lo est\u00e9tica)          Tapicer\u00eda Curo marr\u00f3n          Otros Transmisi\u00f3n trasera y cambio autom\u00e1tico          Carrocer\u00eda Pese a no tener golpes relevantes, tiene algunos da\u00f1os y roces en los paragolpes",
            "Puja m\u00e1s alta": "PREMIUM_INTEGER",
            "Marca": "BMW",
            "Provincia": "-"
        },
        {
            "Identificador": "SUB-AT-2025-25R4186002039",
            "Categor\u00eda": "Turismos",
            "Fin": "2025-09-22",
            "Tasaci\u00f3n": 1710.0,
            "Puja m\u00ednima": 171.0,
            "Tramos": 200,
            "Dep\u00f3sito": 171.0,
            "Descripci\u00f3n": "TURISMO NACIONAL/IMPORTAC 5956CGN  A.U.D.I.  A3 1.6",
            "Puja m\u00e1s alta": "PREMIUM_INTEGER",
            "Marca": "A.U.D.I.",
            "Provincia": "-"
        },
        {
            "Identificador": "SUB-AT-2025-25R4186002053",
            "Categor\u00eda": "Turismos",
            "Fin": "2025-09-15",
            "Tasaci\u00f3n": 2200.0,
            "Puja m\u00ednima": 220.0,
            "Tramos": 200,
            "Dep\u00f3sito": 220.0,
            "Descripci\u00f3n": "TURISMO NACIONAL/IMPORTAC 5628FVG  PEUGEOT  407 SPORT HDI",
            "Puja m\u00e1s alta": "PREMIUM_INTEGER",
            "Marca": "PEUGEOT",
            "Provincia": "-"
        },
        {
            "Identificador": "SUB-AT-2025-25R4786002007",
            "Categor\u00eda": "Turismos",
            "Fin": "2025-09-29",
            "Tasaci\u00f3n": 19700.01,
            "Puja m\u00ednima": 1970.0,
            "Tramos": 500,
            "Dep\u00f3sito": 1970.0,
            "Descripci\u00f3n": "VEHICULO 6881JFW  JAGUAR LAND ROVER LIMIT RANGE ROVER EVOQUE",
            "Puja m\u00e1s alta": "PREMIUM_INTEGER",
            "Marca": "JAGUAR LAND ROVER LIMIT",
            "Provincia": "-"
        },
        {
            "Identificador": "SUB-AT-2025-25R2886002054",
            "Categor\u00eda": "Turismos",
            "Fin": "2025-09-29",
            "Tasaci\u00f3n": 15792.0,
            "Puja m\u00ednima": 1579.2,
            "Tramos": 500,
            "Dep\u00f3sito": 1579.2,
            "Descripci\u00f3n": "FURGONETA 2582LXF  VOLKSWAGEN  CRAFTER",
            "Puja m\u00e1s alta": "PREMIUM_INTEGER",
            "Marca": "VOLKSWAGEN",
            "Provincia": "-"
        },
        {
            "Identificador": "SUB-JA-2025-251005",
            "Categor\u00eda": "Turismos",
            "Fin": "2025-09-29",
            "Tasaci\u00f3n": 3400.0,
            "Puja m\u00ednima": 0.0,
            "Tramos": 68,
            "Dep\u00f3sito": 170.0,
            "Descripci\u00f3n": "Veh\u00edculo BMW 320 D, Bastidor WBAVC31050VB77143",
            "Puja m\u00e1s alta": "PREMIUM_INTEGER",
            "Marca": "BMW",
            "Provincia": "-"
        },
        {
            "Identificador": "SUB-JA-2025-251510",
            "Categor\u00eda": "Turismos",
            "Fin": "2025-09-29",
            "Tasaci\u00f3n": 0.0,
            "Puja m\u00ednima": 0.0,
            "Tramos": 154.7,
            "Dep\u00f3sito": 386.75,
            "Descripci\u00f3n": "VEHICULO MARCA DACIA MODELO DOKKER MATRICULA 7410KLT, BASTIDOR UU10SDCH559949186",
            "Puja m\u00e1s alta": "PREMIUM_INTEGER",
            "Marca": "-",
            "Provincia": "-"
        },
        {
            "Identificador": "SUB-JA-2025-243159",
            "Categor\u00eda": "Turismos",
            "Fin": "2025-09-22",
            "Tasaci\u00f3n": 0.0,
            "Puja m\u00ednima": 0.0,
            "Tramos": "Sin tramos",
            "Dep\u00f3sito": 460.64,
            "Descripci\u00f3n": "veh\u00edculo marca Citro\u00ebn modelo Cactus, matr\u00edcula 7418 KDM, bastidor VF70PHMZBHE544968, inscrito en el Registro de Bienes Muebles de Badajoz",
            "Puja m\u00e1s alta": "PREMIUM_INTEGER",
            "Marca": "-",
            "Provincia": "-"
        },
        {
            "Identificador": "SUB-JV-2025-251320",
            "Categor\u00eda": "Otros",
            "Fin": "2025-09-22",
            "Tasaci\u00f3n": 0.0,
            "Puja m\u00ednima": 800.0,
            "Tramos": 50,
            "Dep\u00f3sito": 320.0,
            "Descripci\u00f3n": "- Identificaci\u00f3n: Ciclomotor de dos ruedas RIEJU MRX          - Matr\u00edcula: C-5224-BSN          - Fecha de matriculaci\u00f3n: 18-08-2006          - Contrase\u00f1a de homologaci\u00f3n: E9*92/61*0074          - Bastidor: VTPMRX11C00619422          - Kil\u00f3metros: Se desconocen. Seg\u00fan la \u00faltima ITV realizada el 25-09-2021, constan 3.224Km          - Carburante: Gasolina          - Cilindrada: 49.0 CC          - Potencia: 1.32 KW / 1.0 CVF          - Documentaci\u00f3n y llaves Hay documentaci\u00f3n del ciclomotor, pero no llave.          - ITV: La \u00faltima ITV se realiz\u00f3 con fecha 25-09-2021, constando          actualmente caducada desde el 25-09-2023.          - Observaciones: Seg\u00fan su titular, el ciclomotor arranca metiendo primera y empujando.",
            "Puja m\u00e1s alta": "PREMIUM_INTEGER",
            "Marca": "RIEJU",
            "Provincia": "Murcia"
        },
        {
            "Identificador": "SUB-JV-2025-251320",
            "Categor\u00eda": "Otros",
            "Fin": "2025-09-22",
            "Tasaci\u00f3n": 0.0,
            "Puja m\u00ednima": 750.0,
            "Tramos": 50,
            "Dep\u00f3sito": 300.0,
            "Descripci\u00f3n": "- Identificaci\u00f3n: Ciclomotor de dos ruedas YAMAHA 5BR          - Matr\u00edcula: C-3174-BDD          - Fecha de matriculaci\u00f3n: 13-01-2000          - Contrase\u00f1a de homologaci\u00f3n: CI-1097          - Bastidor: VG55BR00003530784          - Kil\u00f3metros: Se desconocen. Seg\u00fan la ITV realizada el 11/03/2023, 19.718 Km.          - Carburante: Gasolina          - Color: De varios colores con el logotipo de \u201cREDBULL MONSTER\u201d          - Cilindrada: 49.0 CC          - Potencia: 3.4 KW / 0.01 CVF          - Documentaci\u00f3n y llaves: Hay llave y documentaci\u00f3n de la motocicleta.          - ITV: La \u00faltima ITV se realiz\u00f3 con fecha 11-03-2023, constando actualmente caducada desde el 11-03-2025.          ",
            "Puja m\u00e1s alta": "PREMIUM_INTEGER",
            "Marca": "YAMAHA",
            "Provincia": "Murcia"
        },
        {
            "Identificador": "SUB-AT-2025-25R1586002040",
            "Categor\u00eda": "Turismos",
            "Fin": "2025-09-22",
            "Tasaci\u00f3n": 1820.0,
            "Puja m\u00ednima": 182.0,
            "Tramos": 200,
            "Dep\u00f3sito": 182.0,
            "Descripci\u00f3n": "VEHICULO 0068HSM   HYUNDAI IX20",
            "Puja m\u00e1s alta": "PREMIUM_INTEGER",
            "Marca": "HYUNDAI",
            "Provincia": "-"
        },
        {
            "Identificador": "SUB-AT-2025-25R4186002019",
            "Categor\u00eda": "Turismos",
            "Fin": "2025-09-22",
            "Tasaci\u00f3n": 4743.0,
            "Puja m\u00ednima": 474.3,
            "Tramos": 200,
            "Dep\u00f3sito": 474.3,
            "Descripci\u00f3n": "VEHICULO 1919HXZ   CITROEN NGC4PI",
            "Puja m\u00e1s alta": "PREMIUM_INTEGER",
            "Marca": "CITROEN",
            "Provincia": "-"
        },
        {
            "Identificador": "SUB-AT-2025-25R4186002049",
            "Categor\u00eda": "Turismos",
            "Fin": "2025-09-15",
            "Tasaci\u00f3n": 8970.0,
            "Puja m\u00ednima": 897.0,
            "Tramos": 500,
            "Dep\u00f3sito": 897.0,
            "Descripci\u00f3n": "TURISMO NACIONAL/IMPORTAC 2615KTM  RENAULT  KADJAR",
            "Puja m\u00e1s alta": "PREMIUM_INTEGER",
            "Marca": "RENAULT",
            "Provincia": "-"
        },
        {
            "Identificador": "SUB-RC-2025-2800500102224",
            "Categor\u00eda": "Turismos",
            "Fin": "2025-09-22",
            "Tasaci\u00f3n": 5450.0,
            "Puja m\u00ednima": 545.0,
            "Tramos": 500,
            "Dep\u00f3sito": 545.0,
            "Descripci\u00f3n": "todo terreno 6503FMK",
            "Puja m\u00e1s alta": "PREMIUM_INTEGER",
            "Marca": "VOLVO",
            "Provincia": "Madrid"
        },
        {
            "Identificador": "SUB-JV-2025-251335",
            "Categor\u00eda": "Turismos",
            "Fin": "2025-09-22",
            "Tasaci\u00f3n": 7984.0,
            "Puja m\u00ednima": 3393.2,
            "Tramos": 150,
            "Dep\u00f3sito": 1357.28,
            "Descripci\u00f3n": "Identificaci\u00f3n: Turismo MERCEDES 280 R          Matr\u00edcula: 5551GFL          Fecha de matriculaci\u00f3n: 16-06-2008          Contrase\u00f1a de homologaci\u00f3n: E1*2001/116/0341*05          Bastidor: WDC2511261A084749          Kil\u00f3metros: 339.119 Km.          Carburante: Di\u00e9sel.          Color: Plateado          Cilindrada: 2.987 C.C.          Potencia: 190 CV (140 KW) - 19.92 CVF          Tapicer\u00eda: Mixto textil y cuero negro.          Documentaci\u00f3n y llaves: Hay llave y documentaci\u00f3n (tarjeta de inspecci\u00f3n t\u00e9cnica y fotocopia de permiso de circulaci\u00f3n)          ITV: La \u00faltima inspecci\u00f3n t\u00e9cnica realizada fue el 04-04-2023 y caduc\u00f3 el 04-04-2024          Otros: Transmisi\u00f3n trasera y cambio autom\u00e1tico",
            "Puja m\u00e1s alta": "PREMIUM_INTEGER",
            "Marca": "MERCEDES",
            "Provincia": "Cuenca"
        },
        {
            "Identificador": "SUB-AT-2025-25R4786002008",
            "Categor\u00eda": "Turismos",
            "Fin": "2025-09-29",
            "Tasaci\u00f3n": 9146.0,
            "Puja m\u00ednima": 914.6,
            "Tramos": 500,
            "Dep\u00f3sito": 914.6,
            "Descripci\u00f3n": "FURGONETA 6790KTC  VOLKSWAGEN  CRAFTER",
            "Puja m\u00e1s alta": "PREMIUM_INTEGER",
            "Marca": "VOLKSWAGEN",
            "Provincia": "-"
        },
        {
            "Identificador": "SUB-AT-2025-25R4186002056",
            "Categor\u00eda": "Turismos",
            "Fin": "2025-09-22",
            "Tasaci\u00f3n": 1612.0,
            "Puja m\u00ednima": 161.2,
            "Tramos": 200,
            "Dep\u00f3sito": 161.2,
            "Descripci\u00f3n": "VEHICULO 6272HPY   SMART FORTWO COUPE MHD",
            "Puja m\u00e1s alta": "PREMIUM_INTEGER",
            "Marca": "SMART",
            "Provincia": "-"
        },
        {
            "Identificador": "SUB-AT-2025-25R2886002047",
            "Categor\u00eda": "Turismos",
            "Fin": "2025-09-29",
            "Tasaci\u00f3n": 8073.0,
            "Puja m\u00ednima": 807.3,
            "Tramos": 500,
            "Dep\u00f3sito": 807.3,
            "Descripci\u00f3n": "TURISMO, marca MERCEDES-BENZ modelo CITAN matr\u00edcula:6824KXV",
            "Puja m\u00e1s alta": "PREMIUM_INTEGER",
            "Marca": "MERCEDES-BENZ",
            "Provincia": "-"
        },
        {
            "Identificador": "SUB-AT-2025-25R2886002042",
            "Categor\u00eda": "Turismos",
            "Fin": "2025-09-29",
            "Tasaci\u00f3n": 3050.0,
            "Puja m\u00ednima": 305.0,
            "Tramos": 200,
            "Dep\u00f3sito": 305.0,
            "Descripci\u00f3n": "FURGONETA, marca FORD modelo TRANSIT TOURNEO. Matr\u00edcula: 9218HPB.",
            "Puja m\u00e1s alta": "PREMIUM_INTEGER",
            "Marca": "FORD",
            "Provincia": "-"
        },
        {
            "Identificador": "SUB-JC-2025-246475",
            "Categor\u00eda": "Turismos",
            "Fin": "2025-09-22",
            "Tasaci\u00f3n": 0.0,
            "Puja m\u00ednima": 0.0,
            "Tramos": "Sin tramos",
            "Dep\u00f3sito": 375.0,
            "Descripci\u00f3n": "VEH\u00cdCULO MARCA HYUNDAI, MODELO i30, matr\u00edcula 8389- HTB, NO HAY PUJA M\u00cdNIMA",
            "Puja m\u00e1s alta": "PREMIUM_INTEGER",
            "Marca": "HYUNDAI ",
            "Provincia": "-"
        },
        {
            "Identificador": "SUB-AT-2025-25R4186002043",
            "Categor\u00eda": "Industriales",
            "Fin": "2025-09-29",
            "Tasaci\u00f3n": 2074.0,
            "Puja m\u00ednima": 207.4,
            "Tramos": 200,
            "Dep\u00f3sito": 207.4,
            "Descripci\u00f3n": "VEHICULO MIXTO ADAPTABLE 6884HZD  CITROEN  BERLINGO",
            "Puja m\u00e1s alta": "PREMIUM_INTEGER",
            "Marca": "CITROEN",
            "Provincia": "-"
        },
        {
            "Identificador": "SUB-RC-2025-280050010224",
            "Categor\u00eda": "Turismos",
            "Fin": "2025-09-22",
            "Tasaci\u00f3n": 3077.0,
            "Puja m\u00ednima": 307.7,
            "Tramos": 100,
            "Dep\u00f3sito": 307.7,
            "Descripci\u00f3n": "turismo 7064HSF",
            "Puja m\u00e1s alta": "PREMIUM_INTEGER",
            "Marca": "PEUGEOT",
            "Provincia": "Madrid"
        },
        {
            "Identificador": "SUB-AT-2025-25R4186002037",
            "Categor\u00eda": "Turismos",
            "Fin": "2025-09-15",
            "Tasaci\u00f3n": 2110.0,
            "Puja m\u00ednima": 211.0,
            "Tramos": 200,
            "Dep\u00f3sito": 211.0,
            "Descripci\u00f3n": "TURISMO NACIONAL/IMPORTAC 4988LVJ  RENAULT  KOLEOS",
            "Puja m\u00e1s alta": "PREMIUM_INTEGER",
            "Marca": "RENAULT",
            "Provincia": "-"
        },
        {
            "Identificador": "SUB-RC-2025-0025V20250046",
            "Categor\u00eda": "Turismos",
            "Fin": "2025-09-24",
            "Tasaci\u00f3n": 1800.0,
            "Puja m\u00ednima": 900.0,
            "Tramos": 100,
            "Dep\u00f3sito": 90.0,
            "Descripci\u00f3n": "100,00% de Propiedad plena. Veh\u00edculo 1867GCF LANCIA PHEDRA",
            "Puja m\u00e1s alta": "PREMIUM_INTEGER",
            "Marca": "LANCIA",
            "Provincia": "-"
        },
        {
            "Identificador": "SUB-AT-2025-25R3886002009",
            "Categor\u00eda": "Turismos",
            "Fin": "2025-09-15",
            "Tasaci\u00f3n": 4675.0,
            "Puja m\u00ednima": 467.5,
            "Tramos": 200,
            "Dep\u00f3sito": 467.5,
            "Descripci\u00f3n": "VEHICULO 9975KFX  SEAT LEON",
            "Puja m\u00e1s alta": "PREMIUM_INTEGER",
            "Marca": "SEAT",
            "Provincia": "-"
        },
        {
            "Identificador": "SUB-AT-2025-25R4186002052",
            "Categor\u00eda": "Turismos",
            "Fin": "2025-09-29",
            "Tasaci\u00f3n": 12596.0,
            "Puja m\u00ednima": 1259.6,
            "Tramos": 500,
            "Dep\u00f3sito": 1259.6,
            "Descripci\u00f3n": "TURISMO NACIONAL/IMPORTAC 1702KKW  RENAULT  KOLEOS",
            "Puja m\u00e1s alta": "PREMIUM_INTEGER",
            "Marca": "RENAULT",
            "Provincia": "-"
        },
        {
            "Identificador": "SUB-RC-2025-280050010225",
            "Categor\u00eda": "Turismos",
            "Fin": "2025-09-22",
            "Tasaci\u00f3n": 1790.0,
            "Puja m\u00ednima": 143.2,
            "Tramos": 100,
            "Dep\u00f3sito": 143.2,
            "Descripci\u00f3n": "turismo CA3783BT",
            "Puja m\u00e1s alta": "PREMIUM_INTEGER",
            "Marca": "FORD",
            "Provincia": "Madrid"
        },
        {
            "Identificador": "SUB-AT-2025-25R3586002007",
            "Categor\u00eda": "Turismos",
            "Fin": "2025-09-29",
            "Tasaci\u00f3n": 8413.0,
            "Puja m\u00ednima": 841.3,
            "Tramos": 500,
            "Dep\u00f3sito": 841.3,
            "Descripci\u00f3n": "VEHICULO 0790LLX  CITROEN NUEVO C3 BLUEHDI 100 S",
            "Puja m\u00e1s alta": "PREMIUM_INTEGER",
            "Marca": "CITROEN",
            "Provincia": "-"
        },
        {
            "Identificador": "SUB-JA-2025-251431",
            "Categor\u00eda": "Turismos",
            "Fin": "2025-09-25",
            "Tasaci\u00f3n": 6000.0,
            "Puja m\u00ednima": 2000.0,
            "Tramos": 250,
            "Dep\u00f3sito": 300.0,
            "Descripci\u00f3n": "KIA CEED ",
            "Puja m\u00e1s alta": "PREMIUM_INTEGER",
            "Marca": "KIA",
            "Provincia": "-"
        },
        {
            "Identificador": "SUB-JC-2025-247808",
            "Categor\u00eda": "Turismos",
            "Fin": "2025-09-22",
            "Tasaci\u00f3n": 0.0,
            "Puja m\u00ednima": 100.0,
            "Tramos": "Sin tramos",
            "Dep\u00f3sito": 1000.0,
            "Descripci\u00f3n": "(AVISO: Existe una reserva de dominio a favor de SANTANDER CONSUMER, E.F.C., S.A., que garantiza un cr\u00e9dito privilegiado especial de 24.503,44 euros. Esa reserva ser\u00e1 cancelada cuando se adjudique el veh\u00edculo. El comprador no asume el pago de ese importe y lo adquiere libre de cargas registrales) VEH\u00cdCULO HYUNDAI, modelo Santa Fe. Matr\u00edcula 6169KXH. Fecha de matriculaci\u00f3n 27/05/2019. ITV favorable, vigente hasta el 27 de mayo de 2027. Kilometraje: 88.881 kms. Con seguro en vigor. El veh\u00edculo est\u00e1 en perfecto estado de uso y conservaci\u00f3n, lo est\u00e1 utilizando el mismo concursado. ",
            "Puja m\u00e1s alta": "PREMIUM_INTEGER",
            "Marca": "-",
            "Provincia": "-"
        },
        {
            "Identificador": "SUB-JV-2025-251165",
            "Categor\u00eda": "Turismos",
            "Fin": "2025-09-29",
            "Tasaci\u00f3n": 15986.0,
            "Puja m\u00ednima": 7116.49,
            "Tramos": 450,
            "Dep\u00f3sito": 2846.6,
            "Descripci\u00f3n": "TURISMO          Marca MERCEDES          Modelo CLS350          Matr\u00edcula 4284JLV          Bastidor WDD2183231A081505          Primera matriculaci\u00f3n 13/12/2012          Fecha de matriculaci\u00f3n 16/02/2016          Contrase\u00f1a de homologaci\u00f3n E1*2007/46*0485*07          Carburante Diesel          Color Negro          Cilindrada 2.987cm3          Potencia 261 CV (195Kw)          Kil\u00f3metros 274.824 (seg\u00fan la \u00faltima ITV)          N\u00famero de plazas 5 plazas          Tapicer\u00eda Cuero beige          Otros Transmisi\u00f3n trasera",
            "Puja m\u00e1s alta": "PREMIUM_INTEGER",
            "Marca": "MERCEDES",
            "Provincia": "-"
        },
        {
            "Identificador": "SUB-RC-2025-2800500104323",
            "Categor\u00eda": "Turismos",
            "Fin": "2025-09-22",
            "Tasaci\u00f3n": 5500.0,
            "Puja m\u00ednima": 550.0,
            "Tramos": 500,
            "Dep\u00f3sito": 550.0,
            "Descripci\u00f3n": "turismo 5049LFP",
            "Puja m\u00e1s alta": "PREMIUM_INTEGER",
            "Marca": "SMART",
            "Provincia": "Madrid"
        },
        {
            "Identificador": "SUB-AT-2025-25R2686002001",
            "Categor\u00eda": "Turismos",
            "Fin": "2025-09-15",
            "Tasaci\u00f3n": 2984.37,
            "Puja m\u00ednima": 298.44,
            "Tramos": 200,
            "Dep\u00f3sito": 298.43,
            "Descripci\u00f3n": "TODO TERRENO 1183GJS  B.M.W.  X3 XDRIVE20D",
            "Puja m\u00e1s alta": "PREMIUM_INTEGER",
            "Marca": "B.M.W.",
            "Provincia": "-"
        }
    ],
    "Inmuebles": [
        {
            "Identificador": "SUB-JA-2025-250224",
            "Categor\u00eda": "Vivienda",
            "Fin": "2025-09-15",
            "Tasaci\u00f3n": 0.0,
            "Puja m\u00ednima": 0.0,
            "Tramos": 1160,
            "Dep\u00f3sito": 2900.0,
            "Puja m\u00e1s alta": "PREMIUM_INTEGER",
            "Descripci\u00f3n": "URBANA.- NUEVE.- VIVIENDA en la CUARTA planta o TERCERA planta alta del edificio a que pertenece, portal n\u00famero 15 de la calle San Pedro de Novelda, con una superficie util de sesenta y dos metros , setenta y seis dec\u00edmetros cuadrados. Inscrita en el Registro de la Propiedad n\u00ba 1 de Lleida, al TOMO 1.050, LIBRO 387, FOLIO 35, FINCA REGISTRAL N\u00daMERO 27.966, Inscripci\u00f3n 3. REFERENCIA CATASTRAL N\u00ba 5411520 XH9551S 0007 LB.",
            "Localidad": "PREMIUM_STRING",
            "Provincia": "Alicante/Alacant"
        },
        {
            "Identificador": "SUB-JA-2020-162841",
            "Categor\u00eda": "Vivienda",
            "Fin": "2025-09-11",
            "Tasaci\u00f3n": 0.0,
            "Puja m\u00ednima": 0.0,
            "Tramos": 40000,
            "Dep\u00f3sito": 100000.0,
            "Puja m\u00e1s alta": "PREMIUM_INTEGER",
            "Descripci\u00f3n": "EDIFICACI\u00d3N DE PLANTA BAJA DE 130 METROS CUADRADOS EDIFICADOS, CON UNA SUPERFICIE TOTAL DE 3.112 METROS CUADRADOS",
            "Localidad": "PREMIUM_STRING",
            "Provincia": "Almer\u00eda"
        },
        {
            "Identificador": "SUB-JA-2025-250811",
            "Categor\u00eda": "Vivienda",
            "Fin": "2025-09-29",
            "Tasaci\u00f3n": 0.0,
            "Puja m\u00ednima": 0.0,
            "Tramos": "Sin tramos",
            "Dep\u00f3sito": 7560.0,
            "Puja m\u00e1s alta": "PREMIUM_INTEGER",
            "Descripci\u00f3n": "VIVIENDA TIPO C en planta cuarta del edificio sito en Ja\u00e9n, calle N\u00fa\u00f1ez de Balboa, n\u00famero 25, con la extensi\u00f3n superficial \u00fatil de ochenta y cinco metros cuadrados, y consta de vest\u00edbulo, cuatro dormitorios, comedor, cocina con despensa, cuarto de aseo y terraza- lavadero que da al patio. ",
            "Localidad": "PREMIUM_STRING",
            "Provincia": "Ja\u00e9n"
        },
        {
            "Identificador": "SUB-AT-2025-25R0886001250",
            "Categor\u00eda": "Garaje",
            "Fin": "2025-09-29",
            "Tasaci\u00f3n": 11579.21,
            "Puja m\u00ednima": 926.34,
            "Tramos": 500,
            "Dep\u00f3sito": 463.16,
            "Puja m\u00e1s alta": "PREMIUM_INTEGER",
            "Descripci\u00f3n": "FINCA 31426/DH. URBANA. PLAZA DE APARCAMIENTO NUMERO 172, EN LA PLANTA       SOTANO DEL CONJUNTO RESIDENCIAL ES CAVALL, SITUADA EN EL TERMINO MUNICIPAL   DE CIUTADELLA.TIENE UNA SUPERFICIE DE 11,86M2.",
            "Localidad": "PREMIUM_STRING",
            "Provincia": "Illes Balears"
        },
        {
            "Identificador": "SUB-JA-2025-251415",
            "Categor\u00eda": "Vivienda",
            "Fin": "2025-09-29",
            "Tasaci\u00f3n": 0.0,
            "Puja m\u00ednima": 0.0,
            "Tramos": 3165.79,
            "Dep\u00f3sito": 7914.47,
            "Puja m\u00e1s alta": "PREMIUM_INTEGER",
            "Descripci\u00f3n": "URBANA. OCHO. - VIVIENDA, puerta primera en la planta desv\u00e1n, del edificio sito en el t\u00e9rmino municipal de Aiguafreda con frente al Passeig Catalunya, n\u00famero 37. Linda: frente, con relaci\u00f3n a la fachada del inmueble, parte con el rellano de la escalera por donde tiene su entrada y parte con el vuelo de la zona ajardinada de uso privativo del inmueble; izquierda entrando, parte con la caja de la escalera y parte con la vivienda segunda de la misma planta; derecha entrando, con el vuelo de la rampa de acceso a garaje o planta s\u00f3tano; y al fondo con el vuelo del patio posterior de acceso al garaje o planta s\u00f3tano no edificado",
            "Localidad": "PREMIUM_STRING",
            "Provincia": "Barcelona"
        },
        {
            "Identificador": "SUB-JA-2025-248488",
            "Categor\u00eda": "Solar",
            "Fin": "2025-09-29",
            "Tasaci\u00f3n": 0.0,
            "Puja m\u00ednima": 0.0,
            "Tramos": 1298.2,
            "Dep\u00f3sito": 1622.73,
            "Puja m\u00e1s alta": "PREMIUM_INTEGER",
            "Descripci\u00f3n": "(AVISO. Actualmente solo existe el solar donde se ubicaba la edificaci\u00f3n descrita en el Registro de la Propiedad, ya que, seg\u00fan fotograf\u00edas recientes, ha sido derribada) Es objeto de subasta un solar de 40 m2, situado en la calle Bajada al Puente, en Cieza, aunque registralmente consta la siguiente descripci\u00f3n.URBANA.- En esta ciudad y su calle de Lepanto una casa marcada con el n\u00famero nueve. Compuesta de s\u00f3tano, planta baja y c\u00e1maras. Ocupa una superficie de 43,43 m2. Linda: derecha entrando, calle Ronda Norte; izquierda, parte de la finca de donde \u00e9sta se segreg\u00f3 y Pascual Morcillo Aguilar; y espalda terrapl\u00e9n.  Seg\u00fan referencia catastral de la nota simple,  7533316XH3373D0002EG, es suelo sin edificar de 40 m2. Aunque el solar se ubica actualmente en la calle Bajada al Puente, consta la siguiente direcci\u00f3n catastral: CL PINTOR VELAZQUEZ 1 e/p/p/ /01/0A - 30530 - CIEZA",
            "Localidad": "PREMIUM_STRING",
            "Provincia": "Murcia"
        },
        {
            "Identificador": "SUB-JA-2025-250563",
            "Categor\u00eda": "Finca r\u00fastica",
            "Fin": "2025-09-19",
            "Tasaci\u00f3n": 0.0,
            "Puja m\u00ednima": 0.0,
            "Tramos": 4055.09,
            "Dep\u00f3sito": 10137.73,
            "Puja m\u00e1s alta": "PREMIUM_INTEGER",
            "Descripci\u00f3n": "Suerte de tierras llamada Huerta Nueva en el t\u00e9rmino municipal de Mijas, partido de La Lola. ",
            "Localidad": "PREMIUM_STRING",
            "Provincia": "M\u00e1laga"
        },
        {
            "Identificador": "SUB-AT-2025-25R2886001485",
            "Categor\u00eda": "Solar",
            "Fin": "2025-09-29",
            "Tasaci\u00f3n": 232790.0,
            "Puja m\u00ednima": 18623.2,
            "Tramos": 2000,
            "Dep\u00f3sito": 9311.6,
            "Puja m\u00e1s alta": "PREMIUM_INTEGER",
            "Descripci\u00f3n": "100% PLENO DOMINIO. OBRA NUEVA EN CONSTRUCCI\u00d3N. SUPERFICIE: DEL TERRENO DE   19.018,80 M2. PARCELA D1L1.1 SOBRE LA QUE SE ESTA CONSTRUYENDO LA CANCHA DE  PR\u00c1CTICAS DEL CAMPO DE GOLF, PERTENECIENTE A LA FASE IV DE LA URBANIZACI\u00d3N   DE LOS ANGELES DE SAN RAFAEL, SECTOR  C  DE LAS N.N.S.S. DECLARADA OBRA      NUEVA MEDIANTE ESCRITURA P\u00daBLICA EL 10/07/2008. INSCRIPCI\u00d3N 2\u00aa DE            17/03/2010.",
            "Localidad": "PREMIUM_STRING",
            "Provincia": "Segovia"
        },
        {
            "Identificador": "SUB-NH-2025-1586074",
            "Categor\u00eda": "Vivienda",
            "Fin": "2025-09-22",
            "Tasaci\u00f3n": 0.0,
            "Puja m\u00ednima": 0.0,
            "Tramos": "Sin tramos",
            "Dep\u00f3sito": 0.0,
            "Puja m\u00e1s alta": "PREMIUM_INTEGER",
            "Descripci\u00f3n": "VIVIENDA PISO 5\u00baA PORTAL 2",
            "Localidad": "PREMIUM_STRING",
            "Provincia": "Madrid"
        },
        {
            "Identificador": "SUB-NH-2025-1586074",
            "Categor\u00eda": "Trastero",
            "Fin": "2025-09-22",
            "Tasaci\u00f3n": 0.0,
            "Puja m\u00ednima": 0.0,
            "Tramos": "Sin tramos",
            "Dep\u00f3sito": 0.0,
            "Puja m\u00e1s alta": "PREMIUM_INTEGER",
            "Descripci\u00f3n": "TRASTERO N\u00daMERO 17",
            "Localidad": "PREMIUM_STRING",
            "Provincia": "Madrid"
        },
        {
            "Identificador": "SUB-NH-2025-1586074",
            "Categor\u00eda": "Garaje",
            "Fin": "2025-09-22",
            "Tasaci\u00f3n": 0.0,
            "Puja m\u00ednima": 0.0,
            "Tramos": "Sin tramos",
            "Dep\u00f3sito": 0.0,
            "Puja m\u00e1s alta": "PREMIUM_INTEGER",
            "Descripci\u00f3n": "GARAJE PLAZA N\u00daMERO 23",
            "Localidad": "PREMIUM_STRING",
            "Provincia": "Madrid"
        },
        {
            "Identificador": "SUB-JA-2024-238313",
            "Categor\u00eda": "Vivienda",
            "Fin": "2025-09-22",
            "Tasaci\u00f3n": 105000.0,
            "Puja m\u00ednima": 0.0,
            "Tramos": 2100,
            "Dep\u00f3sito": 5250.0,
            "Puja m\u00e1s alta": "PREMIUM_INTEGER",
            "Descripci\u00f3n": "FINCA REGISTRAL  N\u00ba 23663 ( antes 54694) Registro de la Propiedad n\u00ba 6 de Zaragoza",
            "Localidad": "PREMIUM_STRING",
            "Provincia": "Zaragoza"
        },
        {
            "Identificador": "SUB-JA-2025-250488",
            "Categor\u00eda": "Local comercial",
            "Fin": "2025-09-22",
            "Tasaci\u00f3n": 0.0,
            "Puja m\u00ednima": 0.0,
            "Tramos": "Sin tramos",
            "Dep\u00f3sito": 9500.0,
            "Puja m\u00e1s alta": "PREMIUM_INTEGER",
            "Descripci\u00f3n": "Finca urbana; local sito en planta baja edificio Calle Van Dick n\u00ba35 de Salamanca, con entrada por dicha calle y n\u00famero.",
            "Localidad": "PREMIUM_STRING",
            "Provincia": "Salamanca"
        },
        {
            "Identificador": "SUB-JA-2025-250488",
            "Categor\u00eda": "Finca r\u00fastica",
            "Fin": "2025-09-22",
            "Tasaci\u00f3n": 150000.0,
            "Puja m\u00ednima": 0.0,
            "Tramos": 3000,
            "Dep\u00f3sito": 7500.0,
            "Puja m\u00e1s alta": "PREMIUM_INTEGER",
            "Descripci\u00f3n": "Finca Registral 3.671, inscrita en el Registro de la          Propiedad n\u00fam.2 de salamanca. RUSTICA. - TERRENO en Castellanos de Moriscos (Salamanca), al 4 sitio del Prado del Valle, que mide DOS MIL OCHOCIENTOS metros cuadrados. Ref. Catastral: 1174404TL8417S0001QX. Dentro de la misma existe una casa habitaci\u00f3n de planta baja, que consta de entrada, sal\u00f3n          comedor, cuatro dormitorios, cocina y dos cuartos de ba\u00f1o m\u00e1s          garaje.",
            "Localidad": "PREMIUM_STRING",
            "Provincia": "Salamanca"
        },
        {
            "Identificador": "SUB-AT-2025-25R0886001456",
            "Categor\u00eda": "Garaje",
            "Fin": "2025-09-29",
            "Tasaci\u00f3n": 8325.4,
            "Puja m\u00ednima": 499.52,
            "Tramos": 200,
            "Dep\u00f3sito": 249.76,
            "Puja m\u00e1s alta": "PREMIUM_INTEGER",
            "Descripci\u00f3n": "100% PLENO DOMINIO. URBANA:FINCA ESPECIAL. ELEMENTO NUMERO CUARENTA.-PLAZA   DE APARCAMIENTO, SE\u00d1AL ADO CON EL NUMERO CUARENTA, EN LA PLANTA SOTANO MENOS CINCO DEL EDIFICIO DENO MINADO SANTA ANA II, EN LA CALLE COSTA DE CARBONELL, DE LLORET DE MAR. SUPERF ICIE  OCHO METROS OCHENTA Y SEIS DECIMETROS         CUADRADOS. LINDEROS, ENTRANDO EN LA MISMA  POR EL FRENTE, Y POR LA           IZQUIERDA, CON ZONA COMUN DE MANIOBRA  POR LA DERECHA, CON LA PLAZA DE       APARCAMIENTO NUMERO CUARENTA Y UNO, Y POR DETRAS CON LA PLAZA DE             APARCAMIENTO NUMERO CUARENTA Y DOS. CUOTA DE PARTICIPACION DI EZ CENTESIMAS  POR CIENTO.",
            "Localidad": "PREMIUM_STRING",
            "Provincia": "Girona"
        },
        {
            "Identificador": "SUB-JA-2025-248697",
            "Categor\u00eda": "Vivienda",
            "Fin": "2025-09-29",
            "Tasaci\u00f3n": 0.0,
            "Puja m\u00ednima": 0.0,
            "Tramos": 2340.66,
            "Dep\u00f3sito": 2925.82,
            "Puja m\u00e1s alta": "PREMIUM_INTEGER",
            "Descripci\u00f3n": "URBANA: N\u00daMERO VEINTE.- Forma parte de un edificio construido en t\u00e9rmino de Murcia, partido de Puente Tocinos. Situado en la parcela 4/5 Bis-GER del Pol\u00edgono IV del Plan Parcial \"Puente Tocinos Residencial\", manzana 4/5 bis: VIVIENDA tipo A, seg\u00fan el proyecto, y tipo V2, seg\u00fan la c\u00e9dula de calificaci\u00f3n provisional, de la escalera B, sita en planta baja. Direcci\u00f3n catastral: CL ATLETA ANTONIO PE\u00d1ALVER 1 Es:B Pl:00 Pt:A B/00/A (DH 20) 30006 PUENTE TOCINOS-MURCIA. Distribuida en varias dependencias y servicios.- Superficie \u00fatil 76,30 m2. Tiene como anejo inseparable: la PLAZA DE GARAJE, sita en planta de semis\u00f3tano, se\u00f1alada con el n\u00famero 8. Cuota 2,50 %",
            "Localidad": "PREMIUM_STRING",
            "Provincia": "Murcia"
        },
        {
            "Identificador": "SUB-JA-2025-250480",
            "Categor\u00eda": "Vivienda",
            "Fin": "2025-09-22",
            "Tasaci\u00f3n": 0.0,
            "Puja m\u00ednima": 0.0,
            "Tramos": 804.7,
            "Dep\u00f3sito": 2011.75,
            "Puja m\u00e1s alta": "PREMIUM_INTEGER",
            "Descripci\u00f3n": "URBANA: CUATRO.-          Vivienda en planta primera, del edificio sito en Bigastro, con fachadas a las calles Antonio G\u00e1lvez y Jubilados, sin n\u00famero de demarcaci\u00f3n. Es de tipo B, con fachada a calle Antonio G\u00e1lvez. Tiene una superficie \u00fatil de ochenta y dos metros y sesenta y siete dec\u00edmetros cuadrados, distribuidos en diferentes habitaciones y servicios. Linda seg\u00fan se mira al edificio desde la calle Jubilados: frente, con dicha calle; derecha entrando, con el hueco de escaleras; izquierda, Jes\u00fas Juan Garc\u00eda D\u00edaz; y fondo, con el hueco de escaleras, patio de luces y la otra vivienda de esta planta.",
            "Localidad": "PREMIUM_STRING",
            "Provincia": "Alicante/Alacant"
        },
        {
            "Identificador": "SUB-JA-2025-250549",
            "Categor\u00eda": "Vivienda",
            "Fin": "2025-09-25",
            "Tasaci\u00f3n": 0.0,
            "Puja m\u00ednima": 0.0,
            "Tramos": 3799.58,
            "Dep\u00f3sito": 9498.96,
            "Puja m\u00e1s alta": "PREMIUM_INTEGER",
            "Descripci\u00f3n": "FINCA REGISTRAL 7825",
            "Localidad": "PREMIUM_STRING",
            "Provincia": "Almer\u00eda"
        },
        {
            "Identificador": "SUB-JA-2025-250549",
            "Categor\u00eda": "Garaje",
            "Fin": "2025-09-25",
            "Tasaci\u00f3n": 0.0,
            "Puja m\u00ednima": 0.0,
            "Tramos": 3799.58,
            "Dep\u00f3sito": 9498.96,
            "Puja m\u00e1s alta": "PREMIUM_INTEGER",
            "Descripci\u00f3n": "FINCA REGISTRAL 7913",
            "Localidad": "PREMIUM_STRING",
            "Provincia": "Almer\u00eda"
        },
        {
            "Identificador": "SUB-JA-2025-250549",
            "Categor\u00eda": "Trastero",
            "Fin": "2025-09-25",
            "Tasaci\u00f3n": 0.0,
            "Puja m\u00ednima": 0.0,
            "Tramos": 3799.58,
            "Dep\u00f3sito": 9498.96,
            "Puja m\u00e1s alta": "PREMIUM_INTEGER",
            "Descripci\u00f3n": "FINCA REGISTRAL 8169",
            "Localidad": "PREMIUM_STRING",
            "Provincia": "Almer\u00eda"
        },
        {
            "Identificador": "SUB-JA-2025-246596",
            "Categor\u00eda": "Vivienda",
            "Fin": "2025-09-15",
            "Tasaci\u00f3n": 0.0,
            "Puja m\u00ednima": 0.0,
            "Tramos": 4888,
            "Dep\u00f3sito": 12220.0,
            "Puja m\u00e1s alta": "PREMIUM_INTEGER",
            "Descripci\u00f3n": "DESCRIPCI\u00d3N FINCAINSCRIPCI\u00d3N: Tomo: 2077, Libro 80 Folio 141, finca 2/6263 del RP          n\u00ba VILASECA.",
            "Localidad": "PREMIUM_STRING",
            "Provincia": "Tarragona"
        },
        {
            "Identificador": "SUB-NH-2025-1586075",
            "Categor\u00eda": "Vivienda",
            "Fin": "2025-09-29",
            "Tasaci\u00f3n": 11233.06,
            "Puja m\u00ednima": 56165.34,
            "Tramos": 1000,
            "Dep\u00f3sito": 1123.31,
            "Puja m\u00e1s alta": "PREMIUM_INTEGER",
            "Descripci\u00f3n": "EL 50% DE LA NUDA PROPIEDAD DE UNA VIVIENDA",
            "Localidad": "PREMIUM_STRING",
            "Provincia": "Barcelona"
        },
        {
            "Identificador": "SUB-JA-2025-243010",
            "Categor\u00eda": "Vivienda",
            "Fin": "2025-09-29",
            "Tasaci\u00f3n": 0.0,
            "Puja m\u00ednima": 0.0,
            "Tramos": 0,
            "Dep\u00f3sito": 5509.58,
            "Puja m\u00e1s alta": "PREMIUM_INTEGER",
            "Descripci\u00f3n": "FINCA NUMERO CIENTO UNO.- VIVIENDA LETRA J, ubicada en la planta tercera del Bloque I,          escalera 2, del Edificio en Trobajo del Camino, Ayuntamiento de San Andr\u00e9s del Rabanedo (Le\u00f3n), en          la parcela F. 2 de la Unidad de Ejecuci\u00f3n de Suelo Urbano n\u00famero 17 de las Normas Subsidiarias de          San Andr\u00e9s del Rabanedo. Tiene una superficie construida con participaci\u00f3n en comunes de setenta          y cuatro metros y cincuenta y un dec\u00edmetros cuadrados y est\u00e1 compartimentada en diversas          habitaciones y servicios.",
            "Localidad": "PREMIUM_STRING",
            "Provincia": "Le\u00f3n"
        },
        {
            "Identificador": "SUB-JA-2025-243010",
            "Categor\u00eda": "Garaje",
            "Fin": "2025-09-29",
            "Tasaci\u00f3n": 0.0,
            "Puja m\u00ednima": 0.0,
            "Tramos": 0,
            "Dep\u00f3sito": 535.93,
            "Puja m\u00e1s alta": "PREMIUM_INTEGER",
            "Descripci\u00f3n": "FINCA NUMERO DOCE.- GARAJE NUMERO DOCE ubicado en la planta s\u00f3tano del Bloque 1, del          Edificio en Trobajo del Camino, Ayuntamiento de San Andr\u00e9s del Rabanedo (Le\u00f3n), en la parcela F-2          de la Unidad de Ejecuci\u00f3n de Suelo Urbano n\u00famero 17 de las Normas Subsidiarias de San Andr\u00e9s de          Rabanedo. Tiene una superficie construida con participaci\u00f3n en comunes de treinta metros y sesenta          dec\u00edmetros cuadrados. Linda, tomando como frente el espacio de circulaci\u00f3n y maniobra: Frente,          dicho espacio; Derecha entrando, garaje n\u00famero 13; Izquierda, n\u00facleo de comunicaci\u00f3n vertical de la          escalera 2; Fondo, muro de cerramiento.          CUOTA DE PARTICIPACION: Se le asign\u00f3 en los elementos comunes, beneficios y gastos del          edificio, una cuota de 0,40976\u20ac y de 0,61831\u20ac en el Bloque a que pertenece.",
            "Localidad": "PREMIUM_STRING",
            "Provincia": "Le\u00f3n"
        },
        {
            "Identificador": "SUB-JA-2025-250842",
            "Categor\u00eda": "Vivienda",
            "Fin": "2025-09-24",
            "Tasaci\u00f3n": 0.0,
            "Puja m\u00ednima": 0.0,
            "Tramos": 2045.5,
            "Dep\u00f3sito": 5113.77,
            "Puja m\u00e1s alta": "PREMIUM_INTEGER",
            "Descripci\u00f3n": "SEGUN EDICTO ",
            "Localidad": "PREMIUM_STRING",
            "Provincia": "Valladolid"
        },
        {
            "Identificador": "SUB-AT-2025-25R4186001156",
            "Categor\u00eda": "Vivienda",
            "Fin": "2025-09-22",
            "Tasaci\u00f3n": 47427.09,
            "Puja m\u00ednima": 4742.71,
            "Tramos": 1000,
            "Dep\u00f3sito": 2371.35,
            "Puja m\u00e1s alta": "PREMIUM_INTEGER",
            "Descripci\u00f3n": "69,91% DEL PLENO DOMINIO DE LA PARTE DE LA CASA QUE SE IDENTIFICA CON LAS    INSCRIPCIONES 43\u00aa, 46\u00aa, 55\u00aa Y 56\u00aa. DICHO PORCENTAJE SE CONCRETA EN EL        29,55% DEL PLENO DOMINIO DE LA FINCA REGISTRAL 208: PARTE DE CASA EN LA      CALLE FIERRO, N\u00ba22, DE CHICLANA DE LA FRONTERA, COMPUESTA DE: A) SALA, 3     ALCOBAS Y COCINA EN LA PLANTA ALTA, UNA CUADRA PRIMERA DE LAS DOS A LA       DERECHA ENTRANDO EN EL CORRAL, Y LA TROJA N\u00ba1. B) SALA Y ALCOBA EN LA PLANTA BAJA, , UNA CUADRA QUE ES LA CUARTA PRINCIPIANDO POR LA DERECHA SITUADA EN   EL CORRAL FRENTE A LA PUERTA DE SU ENTRADA, CON LA TROJA N\u00ba 6. C)SALA Y      ALCOBA QUE ES LA PRIMERA HABITACI\u00d3N A LA IZQUIERDA ENTRANDO EN LA CRUJ\u00cdA DE  LA FACHADA, LA CUADRA TERCERA PRINCIPIANDO POR LA DERECHA, LA TROJA N\u00ba 5.",
            "Localidad": "PREMIUM_STRING",
            "Provincia": "C\u00e1diz"
        },
        {
            "Identificador": "SUB-JA-2020-146397",
            "Categor\u00eda": "Vivienda",
            "Fin": "2025-09-17",
            "Tasaci\u00f3n": 0.0,
            "Puja m\u00ednima": 0.0,
            "Tramos": 1317.55,
            "Dep\u00f3sito": 3293.88,
            "Puja m\u00e1s alta": "PREMIUM_INTEGER",
            "Descripci\u00f3n": "FINCA N\u00daMERO CATORCE MIL CIENTO SESENTA Y CINCO DE ASTILLERO DE ASTILLERO INSCRITA EN EL REGISTRO DE LA PROPIEDAD N\u00daMERO DOS DE SANTANDER, TOMO DOS MIL CUATROCIENTOS VEINTINUEVE, FOLIO CIENTO OCHENTA Y SEIS, LIBRO CIENTO CUARENTA Y TRES",
            "Localidad": "PREMIUM_STRING",
            "Provincia": "Cantabria"
        },
        {
            "Identificador": "SUB-JA-2020-146397",
            "Categor\u00eda": "Vivienda",
            "Fin": "2025-09-17",
            "Tasaci\u00f3n": 0.0,
            "Puja m\u00ednima": 0.0,
            "Tramos": 1573.8,
            "Dep\u00f3sito": 3934.5,
            "Puja m\u00e1s alta": "PREMIUM_INTEGER",
            "Descripci\u00f3n": "FINCA CATORCE MIL CIENTO SESENTA Y SIETE DE ASTILLERO, URBANA N\u00daMERO DIECINUEVE  PISO QUINTO LETRA B DEL BLOQUE N\u00daMERO DOS DELGRUPO DE SANTA TERESA EN GURNIZO, INSCRITA EN EL REGISTRO DE LA PROPIEDAD N\u00daMERO 2 DE SANTANDER, TOMO 2429, FOLIO 188, LIBRO 143",
            "Localidad": "PREMIUM_STRING",
            "Provincia": "Cantabria"
        },
        {
            "Identificador": "SUB-JA-2020-146397",
            "Categor\u00eda": "Vivienda",
            "Fin": "2025-09-17",
            "Tasaci\u00f3n": 0.0,
            "Puja m\u00ednima": 0.0,
            "Tramos": 616.07,
            "Dep\u00f3sito": 1540.18,
            "Puja m\u00e1s alta": "PREMIUM_INTEGER",
            "Descripci\u00f3n": "FINCA TREINTA MIL CUATROCIENTOS CUARENTA Y DOS URBANA PISO PRIMERO IZQUIERDA DE UNA CASA SE\u00d1ALADA CON EL N\u00daMERO TREINTA Y SIETEEN EL BARRIO DEL R\u00cdO D ELA PILA DE SANTANDER, INSCRITA EN EL REGISTRO DE LA PROPIEDAD N\u00daMERO UNO DE SANTANDER AL TOMO DOS MIL CIENTO SENTENTA Y CINCO , FOLIO DOSCIENTOS, Y LIBRO NOVECIENTOS CINCO",
            "Localidad": "PREMIUM_STRING",
            "Provincia": "Cantabria"
        },
        {
            "Identificador": "SUB-AT-2025-25R4186001397",
            "Categor\u00eda": "Garaje",
            "Fin": "2025-09-22",
            "Tasaci\u00f3n": 4323.02,
            "Puja m\u00ednima": 345.84,
            "Tramos": 200,
            "Dep\u00f3sito": 172.92,
            "Puja m\u00e1s alta": "PREMIUM_INTEGER",
            "Descripci\u00f3n": "50% DEL PLENO DOMINIO. N\u00daMERO CATORCE.-PLAZA DE APARCAMIENTO EN LA PLANTA    DE SEMIS\u00d3TANO DEL CONJUNTO DE EDIFICACI\u00d3N, EN CALLE VISTA GRANADA, S/N, EN   T\u00c9RMINO DE LAS GABIAS. DONDE SE IDENTIFICA CON EL N\u00daMERO QUINCE  CON ENTRADA A TRAV\u00c9S DE RAMPA DESDE CALLE VISTA GRANADA  TIENE UNA SUPERFICIE \u00daTIL DE    14,86 M2 Y TOTAL CONSTRUIDA CON INCLUSI\u00d3N DE LA PARTE PROPORCIONAL DE        ELEMENTOS COMUNES DE 40,45 M2. LINDA: FRENTE, PASILLO DE MANIOBRA  DERECHA,  APARCAMIENTO 16  IZQUIERDA, EL 14  FONDO, SUBSUELO DEL EDIFICIO.",
            "Localidad": "PREMIUM_STRING",
            "Provincia": "Granada"
        },
        {
            "Identificador": "SUB-AT-2025-25R4786001190",
            "Categor\u00eda": "Garaje",
            "Fin": "2025-09-15",
            "Tasaci\u00f3n": 6500.0,
            "Puja m\u00ednima": 650.0,
            "Tramos": 500,
            "Dep\u00f3sito": 325.0,
            "Puja m\u00e1s alta": "PREMIUM_INTEGER",
            "Descripci\u00f3n": "100% DEL PLENO DOMINIO DE LA FINCA 12009 DE CARBAJOSA DE LA SAGRADA, RP5 DE  SALAMANCA, QUE SEG\u00daN DESCRIPCI\u00d3N REGISTRAL ES URBANA: LOCAL DESTINADO A      GARAJE, EN LA PLANTA DE S\u00d3TANO DEL CONJUNTO INMOBILIARIO EN LA PARCELA       06.04.D DEL PLAN PARCIAL DEL SECTOR I-4  MONTALVO III , CALLE SEGUNDA,       N\u00daMERO DOS. ESTE LOCAL FORMA PARTE DEL CUERPO O BLOQUE DENOMINADO  EDIFICIO  B . EST\u00c1 SE\u00d1ALADO CON EL N\u00daMERO NUEVE. SUPERFICIE CONSTRUIDA 12,77 M2.       LINDA, MIRANDO DESDE LA CALLE SEGUNDA: POR LA DERECHA, PASILLO DE ACCESO Y   MANIOBRA  IZQUIERDA, MURO DE CONTENCI\u00d3N  FONDO, EL LOCAL-GARAJE SE\u00d1ALADO CON EL N\u00daMERO DIEZ  Y POR EL FRENTE, EL SE\u00d1ALADO CON EL N\u00daMERO OCHO. REFERENCIA  CATASTRAL: 6757907TL7365N0009KF.",
            "Localidad": "PREMIUM_STRING",
            "Provincia": "Salamanca"
        },
        {
            "Identificador": "SUB-JA-2025-250351",
            "Categor\u00eda": "Local comercial",
            "Fin": "2025-09-29",
            "Tasaci\u00f3n": 0.0,
            "Puja m\u00ednima": 0.0,
            "Tramos": 1020,
            "Dep\u00f3sito": 2550.0,
            "Puja m\u00e1s alta": "PREMIUM_INTEGER",
            "Descripci\u00f3n": "URBANA.- LOCAL COMERCIAL.- en planta baja o de tierra, con          acceso independiente, que tiene una superficie aproximada de noventa y dos metros cuadrados.          LINDA: Frente o Este, calle de Alicante; OESTE, resto de finca en zona ocupada por la caja          de escalera; Norte, resto de finca en local de Cayetano Blanc; y Sur, dicho resto de finca de          Pedro Villena Navarro.",
            "Localidad": "PREMIUM_STRING",
            "Provincia": "Alicante/Alacant"
        },
        {
            "Identificador": "SUB-JA-2025-248010",
            "Categor\u00eda": "Vivienda",
            "Fin": "2025-09-22",
            "Tasaci\u00f3n": 0.0,
            "Puja m\u00ednima": 0.0,
            "Tramos": "Sin tramos",
            "Dep\u00f3sito": 8628.14,
            "Puja m\u00e1s alta": "PREMIUM_INTEGER",
            "Descripci\u00f3n": "URBANA: FINCA ESPECIAL. ENTIDAD NUMERO DIEZ.- VIVIENDA con balc\u00f3n en voladizo, con sus dependencias y servicios, sita en la PLANTA P-CUATRO, PUERTA TERCERA del edificio que radica en la confluencia de las calles Cerdans y Ferrers, en           a Urbanizaci\u00f3n Mas Baell, del t\u00e9rmino municipal de Lloret de Mar. Tiene una superficie \u00fatil de sesenta y tres metros treinta y dos dec\u00edmetros, cuadrados y una superficie construida de sesenta y nueve metros cincuenta y cuatro dec\u00edmetros, cuadrados. Lindante: al frente, en parte, con rellano com\u00fan de planta por donde se accede, y en parte con la vivienda puerta segunda de esta planta; por la derecha entrando, con la          vivienda puerta segunda de esta planta; por la izquierda entrando, con la vivienda puerta cuarta y en parte con elemento com\u00fan del edificio -ascensor-, y por el fondo, con          la calle dels Ferrers en su proyecci\u00f3n vertical. Coeficiente: cuatro enteros treinta y dos cent\u00e9simas por ciento.",
            "Localidad": "PREMIUM_STRING",
            "Provincia": "Girona"
        },
        {
            "Identificador": "SUB-JA-2025-249998",
            "Categor\u00eda": "Vivienda",
            "Fin": "2025-09-22",
            "Tasaci\u00f3n": 0.0,
            "Puja m\u00ednima": 0.0,
            "Tramos": 5145,
            "Dep\u00f3sito": 12862.5,
            "Puja m\u00e1s alta": "PREMIUM_INTEGER",
            "Descripci\u00f3n": "PISO BAJOS PUERTA PRIMERA del edificio sito en \u00d3DENA calle Manyoses 13. Tiene como anejo la plaza de aparcamiento n\u00fam.9",
            "Localidad": "PREMIUM_STRING",
            "Provincia": "Barcelona"
        },
        {
            "Identificador": "SUB-JA-2025-249998",
            "Categor\u00eda": "Vivienda",
            "Fin": "2025-09-22",
            "Tasaci\u00f3n": 0.0,
            "Puja m\u00ednima": 0.0,
            "Tramos": 3852,
            "Dep\u00f3sito": 9630.0,
            "Puja m\u00e1s alta": "PREMIUM_INTEGER",
            "Descripci\u00f3n": "FINCA 5252, 1\u00ba 21, CALLE MAYOSES 13 DE \u00d6dena APARCAMIENTO 5 (Barcelona) R. Propiedad 1 Igualada",
            "Localidad": "PREMIUM_STRING",
            "Provincia": "Barcelona"
        },
        {
            "Identificador": "SUB-JA-2025-249998",
            "Categor\u00eda": "Vivienda",
            "Fin": "2025-09-22",
            "Tasaci\u00f3n": 0.0,
            "Puja m\u00ednima": 0.0,
            "Tramos": 3192,
            "Dep\u00f3sito": 7980.0,
            "Puja m\u00e1s alta": "PREMIUM_INTEGER",
            "Descripci\u00f3n": "FINCA 5253 R PROPIEDAD 1 IGUALADA PISO 1\u00ba 2\u00ba CALLE MANYOSES 13 \u00d2DENA (BARCELONA)",
            "Localidad": "PREMIUM_STRING",
            "Provincia": "Barcelona"
        },
        {
            "Identificador": "SUB-JA-2025-249998",
            "Categor\u00eda": "Vivienda",
            "Fin": "2025-09-22",
            "Tasaci\u00f3n": 0.0,
            "Puja m\u00ednima": 0.0,
            "Tramos": 4359,
            "Dep\u00f3sito": 10897.5,
            "Puja m\u00e1s alta": "PREMIUM_INTEGER",
            "Descripci\u00f3n": "FINCA 5254 REGISTRO DE LA PROPIEDAD 1 IGUALADA. piso 2\u00ba 1\u00ba calle Manyoses 13. anejo plaza aparcamiento 7-8",
            "Localidad": "PREMIUM_STRING",
            "Provincia": "Barcelona"
        },
        {
            "Identificador": "SUB-JA-2025-249998",
            "Categor\u00eda": "Vivienda",
            "Fin": "2025-09-22",
            "Tasaci\u00f3n": 0.0,
            "Puja m\u00ednima": 0.0,
            "Tramos": 5232,
            "Dep\u00f3sito": 13080.0,
            "Puja m\u00e1s alta": "PREMIUM_INTEGER",
            "Descripci\u00f3n": "FINCA 5255 R PROPIEDAD 1 IGUALADA CALLE MANYOSES 13 2\u00ba 2\u00ba \u00d3DENA (Barcelona) aparcamiento 6",
            "Localidad": "PREMIUM_STRING",
            "Provincia": "Barcelona"
        },
        {
            "Identificador": "SUB-RC-2025-0026I20250115",
            "Categor\u00eda": "Otros",
            "Fin": "2025-09-18",
            "Tasaci\u00f3n": 493120.21,
            "Puja m\u00ednima": 167323.57,
            "Tramos": 3000,
            "Dep\u00f3sito": 16732.36,
            "Puja m\u00e1s alta": "PREMIUM_INTEGER",
            "Descripci\u00f3n": "100,00% de Propiedad plena de RUSTICA.- UNA HECT\u00c1REA, VEINTE \u00c1REAS Y DIEZ CENTI\u00c1REAS de tierra en la Partida del Monj\u00f3n, del t\u00e9rmino municipal de Alicante, Pol\u00edgono 14, parcela 34.- Sobre la misma se halla construido lo siguiente: EDIFICACION DESTINADA A CUADRAS PARA CABALLOS, que ocupan una superficie de seiscientos setenta y ocho metros nueve dec\u00edmetros cuadrados.- UNA VIVIENDA de solo planta baja, distribuida en diversas dependencias y servicios, que ocupa una superficie de veinticuatro metros cincuenta y cinco dec\u00edmetros cuadrados.- EDIFICACI\u00d3N DESTINADA A ALMACENES, sin distribuci\u00f3n interior, que ocupan una superficie de doscientos sesenta y cinco metros cuarenta y dos dec\u00edmetros cuadrados.- EDIFICACI\u00d3N DESTINADA A GUARDA ARNESES, con una superficie de setenta y ocho metros cincuenta y seis dec\u00edmetros cuadrados.- EDIFICACI\u00d3N DESTINADA A BAR, con una superficie de cuarenta y cuatro metros diecinueve dec\u00edmetros cuadrados.- PORCHE, con una superficie de trescientos sesenta metros nueve dec\u00edmetros cuadrados.- Y COBERTIZO, con una superficie de doscientos treinta metros cuarenta y cuatro dec\u00edmetros cuadrados.- Todas las superficies son construidas, y en conjunto suman la cantidad de mil seiscientos ochenta y un metros treinta y cuatro dec\u00edmetros cuadrados.- Ocupa una superficie en parcela de dos mil doscientos setenta y un metros ochenta y siete dec\u00edmetros cuadrados.- LINDAN EN CONJUNTO, por todos sus aires, con la parcela donde se ubican. Y la parcela linda: Norte, con Manuel Pastor Gomis y vesantes; Sur, las de Mar\u00eda Aliaga Gomis; Este, con los herederos de Ram\u00f3n Aliaga y Oeste, con las tierras de los herederos de Mar\u00eda Gomis Garc\u00eda.- Esta finca no est\u00e1 coordinada gr\u00e1ficamente con el Catastro, de conformidad con los arts. 9, 10 y 199 L.H. IDUFIR: 03022000286953.",
            "Localidad": "PREMIUM_STRING",
            "Provincia": "Alicante/Alacant"
        },
        {
            "Identificador": "SUB-JA-2025-242491",
            "Categor\u00eda": "Vivienda",
            "Fin": "2025-09-15",
            "Tasaci\u00f3n": 0.0,
            "Puja m\u00ednima": 0.0,
            "Tramos": 1330.5,
            "Dep\u00f3sito": 3326.25,
            "Puja m\u00e1s alta": "PREMIUM_INTEGER",
            "Descripci\u00f3n": "Finca registral 17495 inscrita en el Registro de la Propiedad de Reus n\u00ba 1, al tomo 1770, libro 1178 y folio 101. ",
            "Localidad": "PREMIUM_STRING",
            "Provincia": "Tarragona"
        },
        {
            "Identificador": "SUB-AT-2025-25R4186001205",
            "Categor\u00eda": "Garaje",
            "Fin": "2025-09-22",
            "Tasaci\u00f3n": 7930.09,
            "Puja m\u00ednima": 634.41,
            "Tramos": 500,
            "Dep\u00f3sito": 317.2,
            "Puja m\u00e1s alta": "PREMIUM_INTEGER",
            "Descripci\u00f3n": "SE ENAJENA EL 100% DEL PLENO DOMINIO DE URBANA: TRECE   EN EL SEMIS\u00d3TANO     DEL EDIFICIO EN LA REDONDELA, T\u00c9RMINO DE ISLA CRISTINA, EN LA CALLE PEDRO    LOPE, SIN N\u00daMERO, ACCEDI\u00c9NDOSE A DICHO SEMIS\u00d3TANO MEDIANTE RAMPA SITA EN LA  CALLE IGLESIA. PLAZA DE GARAJE, SE\u00d1ALADA EN EL SUELO CON PINTURA INDELEBLE   CON EL N\u00daMERO TRECE. TIENE UNA SUPERFICIE APROXIMADA CON INCLUSI\u00d3N DE LA     PARTE PROPORCIONAL EN LAS ZONAS COMUNES DE 27 METROS Y 26 DEC\u00cdMETROS         CUADRADOS.",
            "Localidad": "PREMIUM_STRING",
            "Provincia": "Huelva"
        },
        {
            "Identificador": "SUB-AT-2025-25R2686001023",
            "Categor\u00eda": "Vivienda",
            "Fin": "2025-09-15",
            "Tasaci\u00f3n": 59063.97,
            "Puja m\u00ednima": 3800.19,
            "Tramos": 1000,
            "Dep\u00f3sito": 1900.09,
            "Puja m\u00e1s alta": "PREMIUM_INTEGER",
            "Descripci\u00f3n": "URBANA C/ JOSE ANTONIO PEREZ OTA\u00d1O N\u00ba 2 PLANTA: 3\u00ba PUERTA DCH CP 26580       VIVIENDA DE PROTECCI\u00d3N OFICIAL SUPERFICIE AREA UTIL: 39,85 M 2 N\u00daMERO DE     ORDEN: 26 CUOTA DE PARTICIPACI\u00d3N: 10% . 2% LINDEROS: FRENTE: CON CAJA DE     ESCALERA Y FINCA VEINTICINCO  FONDO: CON CASA CUATRO  IZQUIERDA: CON FINCAS  DERECHA: CON PLAZA  DESCRIPCI\u00d3N DE LA FINCA: NUMERO VEINTISEIS.-VIVIENDA     SITA EN CALLE JOS\u00c9 ANTONIO P\u00c9REZ OTA\u00d1O N O 2 DE ARNEDO, SITUADA EN LA PLANTA TERCERA DERECHA. TIENE UNA SUPERFICIE DE TREINTA Y NUEVE METROS, OCHENTA Y   CINCO DEC\u00cdMETROS CUADRADOS Y CONSTA DE COCINA, SAL\u00d3N-ESTAR, TRES DORMITORIOS Y ASEO.. FINCA NO COORDINADA CON CATASTRO",
            "Localidad": "PREMIUM_STRING",
            "Provincia": "La Rioja"
        },
        {
            "Identificador": "SUB-JA-2025-250155",
            "Categor\u00eda": "Vivienda",
            "Fin": "2025-09-25",
            "Tasaci\u00f3n": 0.0,
            "Puja m\u00ednima": 0.0,
            "Tramos": "Sin tramos",
            "Dep\u00f3sito": 13267.03,
            "Puja m\u00e1s alta": "PREMIUM_INTEGER",
            "Descripci\u00f3n": "finca urbana sita en Calle Goroabe n\u00ba 31- 4\u00ba B de Pamplona- CP: 31005.",
            "Localidad": "PREMIUM_STRING",
            "Provincia": "Navarra"
        },
        {
            "Identificador": "SUB-JA-2025-250336",
            "Categor\u00eda": "Vivienda",
            "Fin": "2025-09-17",
            "Tasaci\u00f3n": 0.0,
            "Puja m\u00ednima": 0.0,
            "Tramos": 5442,
            "Dep\u00f3sito": 13605.0,
            "Puja m\u00e1s alta": "PREMIUM_INTEGER",
            "Descripci\u00f3n": " FINCA REIGSTRAL N\u00ba18.991",
            "Localidad": "PREMIUM_STRING",
            "Provincia": "Madrid"
        },
        {
            "Identificador": "SUB-AT-2025-25R0886001197",
            "Categor\u00eda": "Garaje",
            "Fin": "2025-09-22",
            "Tasaci\u00f3n": 10948.96,
            "Puja m\u00ednima": 656.94,
            "Tramos": 500,
            "Dep\u00f3sito": 328.46,
            "Puja m\u00e1s alta": "PREMIUM_INTEGER",
            "Descripci\u00f3n": "URBANA.- ENTITAT N\u00daMERO DOS.- PLA A D'APARCAMENT N\u00daMERO DOS, SITUADA A LA    PLANTA BAIXA DE L'EDIFICI SITUAT A BALENY\u00c0, AMB FRONT AL CARRER TEIXIDORS,   N\u00daMERO TRES, AMB UNES DIMENSIONS DE QUATRE METRES I VUITANTA-CINC            CENT\u00cdMETRES DE LLARG, PER DOS METRES I QUARANTA-CINC CENT\u00cdMETRES D'AMPLE,    FENT UNA TOTAL SUPERF\u00cdCIE \u00daTIL D'ONZE METRES I VUITANTA-VUIT DEC\u00cdMETRES      QUADRATS. TERMENEJA: AL FRONT, AMB ZONA DE PAS I MANIOBRA  A LA DRETA        ENTRANT, AMB LA PLA A D'APARCAMENT N\u00daMERO U  A L'ESQUERRA ENTRANT, AMB LA    PLA A D'APARCAMENT N\u00daMERO TRES  I AL FONS, AMB M\u00c9S PARET FINAL DE L'EDIFICI. QUOTA DE PARTICIPACI\u00d3: DOS ENTERS I TRENTA CENT\u00c8SIMES PER CENT.",
            "Localidad": "PREMIUM_STRING",
            "Provincia": "Barcelona"
        },
        {
            "Identificador": "SUB-JA-2025-250881",
            "Categor\u00eda": "Finca r\u00fastica",
            "Fin": "2025-09-24",
            "Tasaci\u00f3n": 2074310.48,
            "Puja m\u00ednima": 0.0,
            "Tramos": 41486.2,
            "Dep\u00f3sito": 103715.52,
            "Puja m\u00e1s alta": "PREMIUM_INTEGER",
            "Descripci\u00f3n": "FINCA N\u00ba 160 SITA EN CAS MISSE FIOL- PARCELA 94- POL\u00cdGONO 3- SANTA MARIA DEL CAM\u00cd",
            "Localidad": "PREMIUM_STRING",
            "Provincia": "Illes Balears"
        },
        {
            "Identificador": "SUB-AT-2025-25R0886001226",
            "Categor\u00eda": "Vivienda",
            "Fin": "2025-09-29",
            "Tasaci\u00f3n": 187231.0,
            "Puja m\u00ednima": 14978.48,
            "Tramos": 2000,
            "Dep\u00f3sito": 7489.24,
            "Puja m\u00e1s alta": "PREMIUM_INTEGER",
            "Descripci\u00f3n": "PORCIO DE TERRENY, SITUAT AL TERME MUNICIPAL DE CASTELLCIR, URBANITZACIO LA  PENYORA, CARRER DELS ROSERS,N\u00ba5 QUE CONSTITUEIX LA PARCELA N\u00daMERO 30. SUP    2180,37M2",
            "Localidad": "PREMIUM_STRING",
            "Provincia": "Barcelona"
        },
        {
            "Identificador": "SUB-JA-2025-248733",
            "Categor\u00eda": "Vivienda",
            "Fin": "2025-09-18",
            "Tasaci\u00f3n": 0.0,
            "Puja m\u00ednima": 0.0,
            "Tramos": 2794.5,
            "Dep\u00f3sito": 6986.25,
            "Puja m\u00e1s alta": "PREMIUM_INTEGER",
            "Descripci\u00f3n": "DESCRIPCI\u00d3N:. URBANA: Edificio sito en la Vall de Uxo, Cl. Blasco Iba\u00f1ez n\u00ba79, que ocupa una superficie en cuanto al suelo de 71,50m2; compuesto de planta baja, planta primera alta y planta segunda alta, destinadas todas ellas a una sola vivienda, que ocupa una superficie construida en cuanto a la planta baja de 51,75 m2, y \u00fatil de 43,25 m2, distribuidos en recibidor, cocina, comedor-estar, pasillo, aseo y porche, una superficie construida en cuanto a la primera planta alta de 55,55 m2 y \u00fatil de 46,05 m2, distribuidos en tres habitaciones, distribuidor, ba\u00f1o y terraza y una superficie construida en cuanto a la planta segunda alta de 39,55 m2 y \u00fatil de 34,70 m2, distribuidos en desv\u00e1n y terraza.           Lindes: Frente, la meritada calle y mirando desde la misma, derecha, Josefina Pe\u00f1arroja Rovira; izquierda, Bonifacio Gimenez Molina y fondo, Vicente Valls Nebot.          ",
            "Localidad": "PREMIUM_STRING",
            "Provincia": "Castell\u00f3n/Castell\u00f3"
        },
        {
            "Identificador": "SUB-AT-2025-25R4186001457",
            "Categor\u00eda": "Solar",
            "Fin": "2025-09-15",
            "Tasaci\u00f3n": 648606.48,
            "Puja m\u00ednima": 64860.65,
            "Tramos": 5000,
            "Dep\u00f3sito": 32430.32,
            "Puja m\u00e1s alta": "PREMIUM_INTEGER",
            "Descripci\u00f3n": "SE ENAJENA EL 100 % DEL PLENO DOMINIO DE LA FINCA URBANA: TIENE UNA          SUPERFICIE DE 7.512,45 M2, PARCELA 31.2 DE FORMA RECTANGULAR SITUADA EN PAGO SOLETE BAJO, EN EL T\u00c9RMINO DE JEREZ DE LA FRONTERA. REFERENCIA CATASTRAL     8706905QA5680F0001XS.",
            "Localidad": "PREMIUM_STRING",
            "Provincia": "C\u00e1diz"
        },
        {
            "Identificador": "SUB-JA-2025-250999",
            "Categor\u00eda": "Vivienda",
            "Fin": "2025-09-29",
            "Tasaci\u00f3n": 0.0,
            "Puja m\u00ednima": 0.0,
            "Tramos": "Sin tramos",
            "Dep\u00f3sito": 11688.13,
            "Puja m\u00e1s alta": "PREMIUM_INTEGER",
            "Descripci\u00f3n": "Finca Urbana, apartamento n\u00famero veintisiete. Vivienda piso tercero, puerta C, portal 2, del bloque n\u00famero uno, del Pol\u00edgono Residencial \"El Pilar\", en Chiclana de la Frontera. Tiene una superficie construida de 87,26  metros cuadrados",
            "Localidad": "PREMIUM_STRING",
            "Provincia": "C\u00e1diz"
        }
    ]
}